odoo/addons/sale_order_invoicing_grouping_criteria/README.rst
odoo/addons/sale_order_invoicing_grouping_criteria/__init__.py
odoo/addons/sale_order_invoicing_grouping_criteria/__manifest__.py
odoo/addons/sale_order_invoicing_grouping_criteria/i18n/es.po
odoo/addons/sale_order_invoicing_grouping_criteria/i18n/sale_order_invoicing_grouping_criteria.pot
odoo/addons/sale_order_invoicing_grouping_criteria/models/__init__.py
odoo/addons/sale_order_invoicing_grouping_criteria/models/res_company.py
odoo/addons/sale_order_invoicing_grouping_criteria/models/res_config_settings.py
odoo/addons/sale_order_invoicing_grouping_criteria/models/res_partner.py
odoo/addons/sale_order_invoicing_grouping_criteria/models/sale_invoicing_grouping_criteria.py
odoo/addons/sale_order_invoicing_grouping_criteria/models/sale_order.py
odoo/addons/sale_order_invoicing_grouping_criteria/readme/CONFIGURE.rst
odoo/addons/sale_order_invoicing_grouping_criteria/readme/CONTRIBUTORS.rst
odoo/addons/sale_order_invoicing_grouping_criteria/readme/DESCRIPTION.rst
odoo/addons/sale_order_invoicing_grouping_criteria/readme/INSTALL.rst
odoo/addons/sale_order_invoicing_grouping_criteria/readme/USAGE.rst
odoo/addons/sale_order_invoicing_grouping_criteria/security/ir.model.access.csv
odoo/addons/sale_order_invoicing_grouping_criteria/static/description/icon.png
odoo/addons/sale_order_invoicing_grouping_criteria/static/description/index.html
odoo/addons/sale_order_invoicing_grouping_criteria/tests/__init__.py
odoo/addons/sale_order_invoicing_grouping_criteria/tests/test_sale_order_invoicing_group_criteria.py
odoo/addons/sale_order_invoicing_grouping_criteria/views/res_config_settings_views.xml
odoo/addons/sale_order_invoicing_grouping_criteria/views/res_partner_views.xml
odoo/addons/sale_order_invoicing_grouping_criteria/views/sale_invoicing_grouping_criteria_views.xml
odoo14_addon_sale_order_invoicing_grouping_criteria-14.0.1.0.1.dist-info/METADATA
odoo14_addon_sale_order_invoicing_grouping_criteria-14.0.1.0.1.dist-info/WHEEL
odoo14_addon_sale_order_invoicing_grouping_criteria-14.0.1.0.1.dist-info/top_level.txt
odoo14_addon_sale_order_invoicing_grouping_criteria-14.0.1.0.1.dist-info/RECORD
